odoo8_addon_hr_employee_product-8.0.1.0.0.99.dev3-py2.7-nspkg.pth
odoo8_addon_hr_employee_product-8.0.1.0.0.99.dev3.dist-info/METADATA
odoo8_addon_hr_employee_product-8.0.1.0.0.99.dev3.dist-info/RECORD
odoo8_addon_hr_employee_product-8.0.1.0.0.99.dev3.dist-info/WHEEL
odoo8_addon_hr_employee_product-8.0.1.0.0.99.dev3.dist-info/namespace_packages.txt
odoo8_addon_hr_employee_product-8.0.1.0.0.99.dev3.dist-info/top_level.txt
odoo_addons/hr_employee_product/README.rst
odoo_addons/hr_employee_product/__init__.py
odoo_addons/hr_employee_product/__openerp__.py
odoo_addons/hr_employee_product/i18n/es.po
odoo_addons/hr_employee_product/i18n/fr.po
odoo_addons/hr_employee_product/i18n/hr_employee_product.pot
odoo_addons/hr_employee_product/i18n/sl.po
odoo_addons/hr_employee_product/model/__init__.py
odoo_addons/hr_employee_product/model/hr.py
odoo_addons/hr_employee_product/model/product.py
odoo_addons/hr_employee_product/security/product_security.xml
odoo_addons/hr_employee_product/static/description/icon.png
odoo_addons/hr_employee_product/static/description/index.html
odoo_addons/hr_employee_product/view/product.xml
